{
  "parent": "minecraft:recipes/root",
  "rewards": {
    "recipes": [
      "pl3x:stairs_granite_smooth"
    ]
  },
  "criteria": {
    "has_granite_smooth": {
      "trigger": "minecraft:inventory_changed",
      "conditions": {
        "items": [
          {
            "item": "minecraft:stone",
            "data": 2
          }
        ]
      }
    },
    "has_the_recipe": {
      "trigger": "minecraft:recipe_unlocked",
      "conditions": {
        "recipe": "pl3x:stairs_granite_smooth"
      }
    }
  },
  "requirements": [
    [
      "has_granite_smooth",
      "has_the_recipe"
    ]
  ]
}
